juice_json_schemas/__init__.py
juice_json_schemas/cli.py
juice_json_schemas/py.typed
juice_json_schemas/validation.py
juice_json_schemas-0.0.2.dist-info/LICENSE
juice_json_schemas-0.0.2.dist-info/METADATA
juice_json_schemas-0.0.2.dist-info/WHEEL
juice_json_schemas-0.0.2.dist-info/entry_points.txt
juice_json_schemas-0.0.2.dist-info/RECORD
