Metadata-Version: 2.1
Name: juice-json-schemas
Version: 0.0.2
Summary: Library and utilities for validating JSON files against JUICE mission data schemas or custom JSON Schemas.
Home-page: https://juice-soc.io.esa.int/juice-uplink/spm/juice-json-schemas/
License: MIT
Author: JUICE SOC Team
Author-email: juice_uplink@cosmos.esa.int
Requires-Python: >=3.9,<4.0
Classifier: Development Status :: 4 - Beta
Classifier: Intended Audience :: Developers
Classifier: License :: OSI Approved :: MIT License
Classifier: Operating System :: OS Independent
Classifier: Programming Language :: Python
Classifier: Programming Language :: Python :: 3
Classifier: Programming Language :: Python :: 3.9
Classifier: Programming Language :: Python :: 3.10
Classifier: Programming Language :: Python :: 3.11
Classifier: Programming Language :: Python :: 3.12
Classifier: Topic :: Software Development :: Libraries :: Python Modules
Requires-Dist: jsonschema (>=4.25.1,<5.0.0)
Project-URL: Documentation, https://juice-soc.io.esa.int/juice-uplink/spm/juice-json-schemas/
Project-URL: Repository, https://gitlab.esa.int/juice-soc/juice-uplink/spm/juice-json-schemas.git
